CHANGES.txt
setup.py
oc_tt.egg-info/PKG-INFO
oc_tt.egg-info/SOURCES.txt
oc_tt.egg-info/dependency_links.txt
oc_tt.egg-info/entry_points.txt
oc_tt.egg-info/namespace_packages.txt
oc_tt.egg-info/not-zip-safe
oc_tt.egg-info/requires.txt
oc_tt.egg-info/top_level.txt
opencore/__init__.py
opencore/tasktracker/README.txt
opencore/tasktracker/__init__.py
opencore/tasktracker/configure.zcml
opencore/tasktracker/featurelet.py
opencore/tasktracker/interfaces.py
opencore/tasktracker/tests.py
opencore/tasktracker/browser/__init__.py
opencore/tasktracker/browser/configure.zcml
opencore/tasktracker/testing/__init__.py
opencore/tasktracker/testing/setup.py