Metadata-Version: 1.0
Name: oc-tt
Version: 0.1.2
Summary: opencore tasktracker client package
Home-page: UNKNOWN
Author: The Open Planning Project
Author-email: UNKNOWN
License: GPL
Platform: UNKNOWN
Classifier: Framework :: Plone
Classifier: Framework :: Zope2
Classifier: Framework :: Zope3
Classifier: Programming Language :: Python
Classifier: Topic :: Software Development :: Libraries :: Python Modules
